capychino/__init__.py
capychino-0.0.1.dist-info/METADATA
capychino-0.0.1.dist-info/WHEEL
capychino-0.0.1.dist-info/top_level.txt
capychino-0.0.1.dist-info/RECORD
