Metadata-Version: 2.4
Name: capychino
Version: 0.0.1
Summary: Initial scaffolding - API under active development.
Author-email: OpenTeams <connect@openteams.com>
Requires-Python: >=3.11.7
Requires-Dist: build>=1.3.0
Requires-Dist: twine>=6.2.0
